.bzrignore
.gitignore
.hgignore
.travis.yml
CHANGES.txt
CONTRIBUTORS.txt
COPYRIGHT.txt
HISTORY.txt
LICENSE.txt
README.rst
RELEASING.txt
RESEARCH.txt
TODO.txt
contributing.md
i18n.sh
rtd.txt
setup.cfg
setup.py
tox.ini
deform/TODO
deform/__init__.py
deform/compat.py
deform/decorator.py
deform/exception.py
deform/field.py
deform/form.py
deform/i18n.py
deform/interfaces.py
deform/schema.py
deform/template.py
deform/widget.py
deform/locale/deform.pot
deform/locale/cs/LC_MESSAGES/deform.mo
deform/locale/cs/LC_MESSAGES/deform.po
deform/locale/da/LC_MESSAGES/deform.mo
deform/locale/da/LC_MESSAGES/deform.po
deform/locale/de/LC_MESSAGES/deform.mo
deform/locale/de/LC_MESSAGES/deform.po
deform/locale/el/LC_MESSAGES/deform.mo
deform/locale/el/LC_MESSAGES/deform.po
deform/locale/es/LC_MESSAGES/deform.mo
deform/locale/es/LC_MESSAGES/deform.po
deform/locale/fr/LC_MESSAGES/deform.mo
deform/locale/fr/LC_MESSAGES/deform.po
deform/locale/it/LC_MESSAGES/deform.mo
deform/locale/it/LC_MESSAGES/deform.po
deform/locale/ja/LC_MESSAGES/deform.mo
deform/locale/ja/LC_MESSAGES/deform.po
deform/locale/nl/LC_MESSAGES/deform.mo
deform/locale/nl/LC_MESSAGES/deform.po
deform/locale/pl/LC_MESSAGES/deform.mo
deform/locale/pl/LC_MESSAGES/deform.po
deform/locale/pt/LC_MESSAGES/deform.mo
deform/locale/pt/LC_MESSAGES/deform.po
deform/locale/pt_BR/LC_MESSAGES/deform.mo
deform/locale/pt_BR/LC_MESSAGES/deform.po
deform/locale/ru/LC_MESSAGES/deform.mo
deform/locale/ru/LC_MESSAGES/deform.po
deform/locale/sv/LC_MESSAGES/deform.mo
deform/locale/sv/LC_MESSAGES/deform.po
deform/locale/zh/LC_MESSAGES/deform.mo
deform/locale/zh/LC_MESSAGES/deform.po
deform/static/css/beautify.css
deform/static/css/bootstrap.min.css
deform/static/css/form.css
deform/static/css/pickadate-classic.date.min.css
deform/static/css/pickadate-classic.min.css
deform/static/css/typeahead.css
deform/static/fonts/glyphicons-halflings-regular.eot
deform/static/fonts/glyphicons-halflings-regular.svg
deform2000.egg-info/PKG-INFO
deform2000.egg-info/SOURCES.txt
deform2000.egg-info/dependency_links.txt
deform2000.egg-info/not-zip-safe
deform2000.egg-info/requires.txt
deform2000.egg-info/top_level.txt
